netsuite_db_connector/__init__.py
netsuite_db_connector/extract.py
netsuite_db_connector/extract_ddl.sql
netsuite_db_connector/load.py
netsuite_db_connector/load_ddl.sql
netsuite_db_connector-0.3.1.dist-info/LICENSE
netsuite_db_connector-0.3.1.dist-info/METADATA
netsuite_db_connector-0.3.1.dist-info/WHEEL
netsuite_db_connector-0.3.1.dist-info/top_level.txt
netsuite_db_connector-0.3.1.dist-info/RECORD
