Metadata-Version: 2.1
Name: netsuite-db-connector
Version: 0.3.1
Summary: Connects NetSuite to a database connector to transfer information to and fro
Home-page: https://github.com/fylein/netsuite-db-connector
Author: Siva Narayanan
Author-email: siva@fyle.in
License: MIT
Keywords: netsuite,api,python,sdk,sqlite
Platform: UNKNOWN
Classifier: Topic :: Internet :: WWW/HTTP
Classifier: Intended Audience :: Developers
Classifier: Programming Language :: Python :: 3
Classifier: License :: OSI Approved :: MIT License
Classifier: Operating System :: OS Independent
Requires-Dist: netsuitesdk (==1.12.0)
